.gitignore
LICENSE
PKG-INFO
README.md
__init__.py
__main__.py
localpy.py
pyproject.toml
requirements.txt
localpy/LICENSE
localpy/README.md
localpy/__init__.py
localpy/__main__.py
localpy/localpy.py
localpy/pyproject.toml
localpy/requirements.txt
localpy-1.0.6.dist-info/METADATA
localpy-1.0.6.dist-info/WHEEL
localpy-1.0.6.dist-info/entry_points.txt
localpy-1.0.6.dist-info/licenses/LICENSE
localpy-1.0.6.dist-info/RECORD
