Metadata-Version: 2.4
Name: localpy
Version: 1.0.6
Summary: A commandline tool for storing passwords safely on your computer.
Project-URL: Homepage, https://github.com/pypa/sampleproject
Project-URL: Issues, https://github.com/pypa/sampleproject/issues
Author-email: Speartech <Tyler@Speartech.org>
License-File: LICENSE
Classifier: License :: OSI Approved :: MIT License
Classifier: Operating System :: OS Independent
Classifier: Programming Language :: Python :: 3
Requires-Python: >=3.11
Requires-Dist: cffi==1.15.1
Requires-Dist: cryptography==38.0.3
Requires-Dist: pycparser==2.21
Requires-Dist: pyperclip==1.8.2
Requires-Dist: requests==2.28.1
Requires-Dist: urllib3==1.26.12
